Metadata-Version: 2.1
Name: GamepayPy
Version: 1.0.0
Summary: Easy way to work with GamePay.best API
Home-page: UNKNOWN
Author-email: leetcrash.official@gmail.com
License: UNKNOWN
Platform: UNKNOWN
